pingplot/__init__.py
pingplot/__main__.py
pingplot/plotping.py
pingplot-0.1.3.dist-info/entry_points.txt
pingplot-0.1.3.dist-info/METADATA
pingplot-0.1.3.dist-info/WHEEL
pingplot-0.1.3.dist-info/RECORD
